setup.py
linsensors/__init__.py
linsensors/adt7410.py
linsensors/ai418s.py
linsensors/bmp180.py
linsensors/ezo.py
linsensors/htu21d.py
linsensors/max31855.py
linsensors/max6675.py
linsensors/mcp4725.py
linsensors/mpl115a2.py
linsensors/one_wire_temp.py
linsensors/sensorbase.py
linsensors/tsl2561.py
linsensors.egg-info/PKG-INFO
linsensors.egg-info/SOURCES.txt
linsensors.egg-info/dependency_links.txt
linsensors.egg-info/requires.txt
linsensors.egg-info/top_level.txt