Metadata-Version: 1.1
Name: linsensors
Version: 0.0.3
Summary: Interface with embedded sensors in linux through i2c, spi, etc
Home-page: https://github.com/cloudformdesign/linsensors
Author: Garrett Berg
Author-email: garrett@cloudformdesign.com
License: MIT
Platform: UNKNOWN
Classifier: Intended Audience :: Developers
Classifier: License :: OSI Approved :: MIT License
Classifier: Operating System :: OS Independent
Classifier: Programming Language :: Python :: 2.7
Classifier: Programming Language :: Python :: 3
Classifier: Programming Language :: Python :: 3.4
Classifier: Topic :: Software Development :: Embedded Systems
Classifier: Topic :: Software Development :: Libraries :: Python Modules
